LICENSE.txt
MANIFEST.in
README.rst
README.txt
requirements.txt
setup.py
TrelloCardUpdate.egg-info/PKG-INFO
TrelloCardUpdate.egg-info/SOURCES.txt
TrelloCardUpdate.egg-info/dependency_links.txt
TrelloCardUpdate.egg-info/requires.txt
TrelloCardUpdate.egg-info/top_level.txt
bin/tu
bin/tu.py
docs/design.txt
trellocardupdate/__init__.py
trellocardupdate/cli.py
trellocardupdate/external_editor.py
trellocardupdate/local.py
trellocardupdate/simpledispatchargparse.py
trellocardupdate/trelloupdate.py
trellocardupdate/test/__init__.py