Metadata-Version: 1.0
Name: TrelloCardUpdate
Version: 0.0.8
Summary: basic command line trello client
Home-page: https://github.com/thomasballinger/trellocardupdate
Author: Thomas Ballinger
Author-email: tom@hackerschool.com
License: LICENSE.txt
Platform: UNKNOWN
